CHANGES.txt
PKG-INFO
README.md
setup.cfg
setup.py
hostout/__init__.py
hostout.overridedeploy.egg-info/PKG-INFO
hostout.overridedeploy.egg-info/SOURCES.txt
hostout.overridedeploy.egg-info/dependency_links.txt
hostout.overridedeploy.egg-info/entry_points.txt
hostout.overridedeploy.egg-info/namespace_packages.txt
hostout.overridedeploy.egg-info/not-zip-safe
hostout.overridedeploy.egg-info/requires.txt
hostout.overridedeploy.egg-info/top_level.txt
hostout/overridedeploy/__init__.py
hostout/overridedeploy/fabfile.py