Metadata-Version: 1.0
Name: hostout.overridedeploy
Version: 1.0
Summary: override default deploy of hostout
Home-page: https://svn.andersonleeb.com/hostout.overridedeploy
Author: Anderson Leeb Inc
Author-email: admin@andersonleeb.com
License: GPL
Keywords: buildout,fabric,deploy,deployment,server,plone,django,host,hosting
Platform: UNKNOWN
